logging_mv_integrations/__init__.py
logging_mv_integrations/logger_adapter_custom.py
logging_mv_integrations/logger_json_lexer.py
logging_mv_integrations/logging.py
logging_mv_integrations/logging_format.py
logging_mv_integrations/logging_json_formatter.py
logging_mv_integrations/logging_levels.py
logging_mv_integrations/logging_output.py
logging_mv_integrations/errors/__init__.py
logging_mv_integrations/errors/errors_traceback.py
logging_mv_integrations/support/__init__.py
logging_mv_integrations/support/singleton.py
logging_mv_integrations-0.5.4.dist-info/DESCRIPTION.rst
logging_mv_integrations-0.5.4.dist-info/METADATA
logging_mv_integrations-0.5.4.dist-info/RECORD
logging_mv_integrations-0.5.4.dist-info/WHEEL
logging_mv_integrations-0.5.4.dist-info/metadata.json
logging_mv_integrations-0.5.4.dist-info/top_level.txt
