Metadata-Version: 2.0
Name: logging-mv-integrations
Version: 0.5.4
Summary: Extension to Python `logging` functionality intended for TUNE Multiverse Integrations.
Home-page: https://github.com/TuneLab/logging-mv-integrations
Author: TUNE Inc.
Author-email: jefft@tune.com
License: MIT License
Download-URL: https://github.com/TuneLab/logging-mv-integrations/archive/v0.5.4.tar.gz
Keywords: logging tune
Platform: UNKNOWN
Classifier: Development Status :: 5 - Production/Stable
Classifier: Intended Audience :: Developers
Classifier: Natural Language :: English
Classifier: License :: OSI Approved :: MIT License
Classifier: Operating System :: OS Independent
Classifier: Natural Language :: English
Classifier: Programming Language :: Python
Classifier: Programming Language :: Python :: 3
Classifier: Programming Language :: Python :: 3.4
Classifier: Programming Language :: Python :: 3.5
Classifier: Programming Language :: Python :: 3.6
Classifier: Topic :: Software Development :: Libraries :: Python Modules
Requires-Dist: coloredlogs (>=7.3)
Requires-Dist: python-json-logger (>=0.1.8)
Requires-Dist: pprintpp (>=0.3.0)
Requires-Dist: Pygments (>=2.2.0)
Requires-Dist: pytest (>=3.2.3)
Requires-Dist: pytest-mock (>=1.6.3)
Requires-Dist: pytest-cov (>=2.5.1)
Requires-Dist: safe-cast (>=0.1.1)
Requires-Dist: tzlocal (>=1.4)
Requires-Dist: wheel (>=0.30.0)
